[
        {
            "nama": "Asus Ebook E203MAH",
            
                "gambar": "/images/laptop/l1.jpg",
                "deskripsi": "Intel Coleron N4000 Processor | Windows 10 Home | Layar 11.6in HD (1366x768) | Grafis Intel HD | 500GB HDD | 4GB / 2GB LPDDR4 Memory | USB 3.1 Type-C, USB 3.0, BT 4.0, Wi-Fi | 1 tahun garansi global",
                "harga": "Rp. 3.499.000"
            
        },
        {
            "nama": "ASUS VivoBook A407UB",
            
                "gambar": "/images/laptop/l2.jpg",
                "deskripsi": "Intel Core i3-7100U Processor | Windows 10 Home | Layar 14in HD (1366x768) | Discret Graphics MX 110-2GB | 1TB HDD | 4GB DRR4 Memory | USB 3.0, BT 4.1, Wi-Fi, 802-11 ac | 2 tahun garansi global",
                "harga": "Rp. 6.549.000"
            
        },
        {
            "nama": "ROG Zephyrus GX501GI G-SYNC",
            
                "gambar": "/images/laptop/l3.jpg",
                "deskripsi": "Intel Core i7-7700HQ Processor | Windows 10 Home | Layar 15.6in IPS FHD Anti Glare (1920x1080) 144Hz 3ms | Discret Graphics GTX-1080 Max-Q-8GB GDDR5 + G Sync | 512GB NVMe PCIe G3x4 SSD | 24GB DRR4 Memory | USB 3.0, USB 3.1, BT 4.1, Wi-Fi | 2 tahun garansi global",
                "harga": "Rp. 51.299.000"
            
        },

        {
            "nama": "ADVAN i6A",
                "gambar": "/images/hp/h1.jpg",
                "deskripsi": "5.5in IPS Full View | 2 GB RAM - 16GB ROM | 13MP Rear Camera - 5MP Front Camera | 3200mAh",
                "harga": "Rp. 999.000"
            
        },
        {
            "nama": "Xiaomi Redmi Note 5A",
                "gambar": "/images/hp/h2.jpg",
                "deskripsi": "5.5in IPS LCD | 3 GB RAM - 32GB ROM | 13MP Rear Camera - 16MP Front Camera | 3080mAh",
                "harga": "Rp. 1.150.000"
            
        },
        {
            "nama": "Samsung GALAXY S6",
            
                "gambar": "/images/hp/h3.jpg",
                "deskripsi": "5.1in Super Inch AMOLED | 3 GB RAM - 32GB ROM | 16MP Rear Camera - 5MP Front Camera | 2550mAh",
                "harga": "Rp. 2.100.000"
            
        },

        {
            "nama": "Printer EPSON L3110",
            
                "gambar": "/images/dll/d1.jpg",
                "deskripsi": "Features : print, scan, copy, borderless printing up to 4R | 33/15ppm Speed | Resolution 5760x1440dpi Max Print, 600x1200dpi Scanner Optical | Ink Model 003 | 2 tahun garansi",
                "harga": "Rp. 1.990.000"
            
        },
        {
            "nama": "Flashdisk TOSHIBA U202",
        
                "gambar": "/images/dll/d2.jpg",
                "deskripsi": "32GB | USB Type-A | Operating Temperature : 0-50 C | Interface USB 2.0 High-Speed | Compatible Machine Windows PC atau Mac | Required OS Windows 7, Windows 8.1, Windows 10, OS X v10.9-v10.11",
                "harga": "Rp. 38.000"
            
        },
        {
            "nama": "Headphone Sony EXTRA BASS MDR-XB450AP",
            
                "gambar": "/images/dll/d3.jpg",
                "deskripsi": "Unit Driver 30mm | Respons Frekuensi 5Hz-22kHz | panjang kabel 1.2m | Input 3.5mm jack",
                "harga": "Rp. 36.000"
            
        }
]
